AUTHORS.rst
CHANGELOG.rst
LICENSE.txt
MANIFEST.in
README.rst
requirements-dev.txt
requirements.txt
setup.py
bin/hex2words
hex2words/__init__.py
hex2words/hex2words.py
hex2words/input.py
hex2words/program.py
hex2words/version.py
hex2words.egg-info/PKG-INFO
hex2words.egg-info/SOURCES.txt
hex2words.egg-info/dependency_links.txt
hex2words.egg-info/top_level.txt
hex2words.egg-info/zip-safe