Metadata-Version: 1.1
Name: hex2words
Version: 0.1.0
Summary: Hexadecimal ID/Fingerprint to PGP-words list converter
Home-page: https://bitbucket.org/pfigue/hex2words
Author: Pablo Figue
Author-email: pfigue posteo de
License: MIT
Keywords: hexadecimal,fingerprint,gpg,pgp,pgp words
Platform: UNKNOWN
Classifier: Development Status :: 3 - Alpha
Classifier: Environment :: Console
Classifier: Intended Audience :: Developers
Classifier: Intended Audience :: Information Technology
Classifier: Intended Audience :: System Administrators
Classifier: Intended Audience :: Telecommunications Industry
Classifier: License :: OSI Approved :: MIT License
Classifier: Operating System :: OS Independent
Classifier: Programming Language :: Python :: 2
Classifier: Programming Language :: Python :: 2.7
Classifier: Programming Language :: Python :: 3
Classifier: Programming Language :: Python :: 3.4
Classifier: Programming Language :: Python :: Implementation :: CPython
Classifier: Programming Language :: Python :: Implementation :: PyPy
Classifier: Topic :: Artistic Software
Classifier: Topic :: Security
